pd_cldf/__init__.py
pd_cldf-0.0.1.dist-info/LICENSE
pd_cldf-0.0.1.dist-info/METADATA
pd_cldf-0.0.1.dist-info/WHEEL
pd_cldf-0.0.1.dist-info/top_level.txt
pd_cldf-0.0.1.dist-info/RECORD
